{
  "docusaurus-plugin-content-docs": {
    "default": {
      "path": "/docs",
      "versions": [
        {
          "name": "current",
          "label": "Next",
          "isLast": true,
          "path": "/docs",
          "mainDocId": "intro",
          "docs": [
            {
              "id": "intro",
              "path": "/docs/intro",
              "sidebar": "tutorialSidebar"
            },
            {
              "id": "original/Bounty-Managment",
              "path": "/docs/original/Bounty-Managment",
              "sidebar": "tutorialSidebar"
            },
            {
              "id": "original/Curators-&-Advisors",
              "path": "/docs/original/Curators-&-Advisors",
              "sidebar": "tutorialSidebar"
            },
            {
              "id": "original/Development-Requirements",
              "path": "/docs/original/Development-Requirements",
              "sidebar": "tutorialSidebar"
            },
            {
              "id": "original/External-links",
              "path": "/docs/original/External-links",
              "sidebar": "tutorialSidebar"
            },
            {
              "id": "original/Home",
              "path": "/docs/original/Home",
              "sidebar": "tutorialSidebar"
            },
            {
              "id": "original/Meetings-&-Announcements",
              "path": "/docs/original/Meetings-&-Announcements",
              "sidebar": "tutorialSidebar"
            },
            {
              "id": "original/Membership",
              "path": "/docs/original/Membership",
              "sidebar": "tutorialSidebar"
            },
            {
              "id": "original/SLA-Checks",
              "path": "/docs/original/SLA-Checks",
              "sidebar": "tutorialSidebar"
            },
            {
              "id": "original/Support",
              "path": "/docs/original/Support",
              "sidebar": "tutorialSidebar"
            },
            {
              "id": "server/first-access",
              "path": "/docs/server/first-access",
              "sidebar": "tutorialSidebar"
            },
            {
              "id": "/category/original-wiki-content",
              "path": "/docs/category/original-wiki-content",
              "sidebar": "tutorialSidebar"
            },
            {
              "id": "/category/tutorial---basic-server",
              "path": "/docs/category/tutorial---basic-server",
              "sidebar": "tutorialSidebar"
            }
          ],
          "draftIds": [],
          "sidebars": {
            "tutorialSidebar": {
              "link": {
                "path": "/docs/intro",
                "label": "intro"
              }
            }
          }
        }
      ],
      "breadcrumbs": true
    }
  }
}